mlcorelib.py
mlcorelib-0.1.6.dist-info/METADATA
mlcorelib-0.1.6.dist-info/WHEEL
mlcorelib-0.1.6.dist-info/top_level.txt
mlcorelib-0.1.6.dist-info/RECORD
