Metadata-Version: 2.1
Name: mlcorelib
Version: 0.1.6
Summary: Provides library for ML
Home-page: UNKNOWN
Author: Avinash Saxena
License: UNKNOWN
Platform: UNKNOWN
Classifier: Programming Language :: Python :: 3
Classifier: License :: OSI Approved :: MIT License
Classifier: Operating System :: OS Independent
Requires-Python: >=3.6
Requires-Dist: transformers
Requires-Dist: sklearn
Requires-Dist: numpy
